scrapery/__init__.py
scrapery/exceptions.py
scrapery/html_api.py
scrapery/html_elements.py
scrapery/json_api.py
scrapery/json_elements.py
scrapery/utils.py
scrapery/xml_api.py
scrapery/xml_api_backup.py
scrapery/xml_elements.py
scrapery/xml_html.py
scrapery-0.1.22.dist-info/METADATA
scrapery-0.1.22.dist-info/WHEEL
scrapery-0.1.22.dist-info/top_level.txt
scrapery-0.1.22.dist-info/RECORD
