Metadata-Version: 2.4
Name: scrapery
Version: 0.1.22
Summary: Scrapery: A fast, lightweight library to scrape HTML, XML, and JSON using XPath, CSS selectors, and intuitive DOM navigation.
Author: Ramesh Chandra
Author-email: rameshsofter@gmail.com
License: MIT
Project-URL: Documentation, https://scrapery.readthedocs.io/en/latest/
Keywords: web scraping,html parser,xml parser,json parser,lxml,ujson,data extraction,scraping tools
Classifier: Programming Language :: Python :: 3
Classifier: Programming Language :: Python :: 3.8
Classifier: License :: OSI Approved :: MIT License
Classifier: Operating System :: OS Independent
Classifier: Topic :: Software Development :: Libraries :: Python Modules
Classifier: Topic :: Utilities
Classifier: Intended Audience :: Developers
Classifier: Natural Language :: English
Requires-Python: >=3.8
Requires-Dist: lxml
Requires-Dist: cssselect
Requires-Dist: ujson
Requires-Dist: chardet
Requires-Dist: jmespath
Requires-Dist: ftfy
Requires-Dist: ijson
Requires-Dist: pandas
Requires-Dist: tldextract
Requires-Dist: openpyxl
Dynamic: author
Dynamic: author-email
Dynamic: classifier
Dynamic: description
Dynamic: description-content-type
Dynamic: keywords
Dynamic: license
Dynamic: project-url
Dynamic: requires-dist
Dynamic: requires-python
Dynamic: summary
